unblocked.py
unblocked-0.1.0.dist-info/METADATA
unblocked-0.1.0.dist-info/WHEEL
unblocked-0.1.0.dist-info/licenses/LICENSE
unblocked-0.1.0.dist-info/RECORD
