Metadata-Version: 2.1
Name: unblocked
Version: 0.1.0
Summary: Simple and clean background tasks.
Project-URL: Homepage, https://github.com/twanwalpot/unblocked
Project-URL: Bug Tracker, https://github.com/twanwalpot/unblocked/issues
Author-email: Twan Walpot <twan@walpot.dev>
License: MIT License
Classifier: License :: OSI Approved :: MIT License
Classifier: Operating System :: OS Independent
Classifier: Programming Language :: Python :: 3
Requires-Python: >=3.7
